LICENSE
MANIFEST.in
README.md
dev.txt
setup.py
scourge/__init__.py
scourge/debug.py
scourge/fedex.py
scourge/metro.py
scourge/metro_orders.py
scourge/non_stop_delivery.py
scourge/pilot.py
scourge/ups.py
scourge/version.txt
scourge.egg-info/PKG-INFO
scourge.egg-info/SOURCES.txt
scourge.egg-info/dependency_links.txt
scourge.egg-info/requires.txt
scourge.egg-info/top_level.txt